django_search_arrayfield/__init__.py
django_search_arrayfield/apps.py
django_search_arrayfield/admin/__init__.py
django_search_arrayfield/admin/mixins.py
django_search_arrayfield/forms/__init__.py
django_search_arrayfield/forms/fields.py
django_search_arrayfield/forms/widgets.py
django_search_arrayfield/migrations/__init__.py
django_search_arrayfield/models/__init__.py
django_search_arrayfield/models/fields.py
django_search_arrayfield/static/css/django_search_arrayfield.min.css
django_search_arrayfield/static/js/django_search_arrayfield.min.js
django_search_arrayfield/templates/django_search_arrayfield/forms/widgets/dynamic_array.html
django_search_arrayfield-1.2.3.dist-info/LICENSE.md
django_search_arrayfield-1.2.3.dist-info/METADATA
django_search_arrayfield-1.2.3.dist-info/WHEEL
django_search_arrayfield-1.2.3.dist-info/top_level.txt
django_search_arrayfield-1.2.3.dist-info/RECORD
